TineAppiumFlutterLibrary/__init__.py
TineAppiumFlutterLibrary/version.py
TineAppiumFlutterLibrary/keywords/__init__.py
TineAppiumFlutterLibrary/keywords/_logging.py
TineAppiumFlutterLibrary/keywords/_runonfailure.py
TineAppiumFlutterLibrary/keywords/_support.py
TineAppiumFlutterLibrary/keywords/_supportelement.py
TineAppiumFlutterLibrary/keywords/keywordgroup.py
TineAppiumFlutterLibrary-1.1.0.dist-info/LICENSE
TineAppiumFlutterLibrary-1.1.0.dist-info/METADATA
TineAppiumFlutterLibrary-1.1.0.dist-info/WHEEL
TineAppiumFlutterLibrary-1.1.0.dist-info/top_level.txt
TineAppiumFlutterLibrary-1.1.0.dist-info/RECORD
